django2_markdown-0.8.6.dist-info/DESCRIPTION.rst
django2_markdown-0.8.6.dist-info/METADATA
django2_markdown-0.8.6.dist-info/RECORD
django2_markdown-0.8.6.dist-info/WHEEL
django2_markdown-0.8.6.dist-info/metadata.json
django2_markdown-0.8.6.dist-info/top_level.txt
django_markdown/__init__.py
django_markdown/admin.py
django_markdown/fields.py
django_markdown/flatpages.py
django_markdown/models.py
django_markdown/pypandoc.py
django_markdown/settings.py
django_markdown/tests.py
django_markdown/urls.py
django_markdown/utils.py
django_markdown/views.py
django_markdown/widgets.py
django_markdown/static/django_markdown/jquery.init.js
django_markdown/static/django_markdown/jquery.markitup.js
django_markdown/static/django_markdown/preview.css
django_markdown/static/django_markdown/sets/markdown/set.js
django_markdown/static/django_markdown/sets/markdown/style.css
django_markdown/static/django_markdown/sets/markdown/images/bold.png
django_markdown/static/django_markdown/sets/markdown/images/clean.png
django_markdown/static/django_markdown/sets/markdown/images/code.png
django_markdown/static/django_markdown/sets/markdown/images/h1.png
django_markdown/static/django_markdown/sets/markdown/images/h2.png
django_markdown/static/django_markdown/sets/markdown/images/h3.png
django_markdown/static/django_markdown/sets/markdown/images/h4.png
django_markdown/static/django_markdown/sets/markdown/images/h5.png
django_markdown/static/django_markdown/sets/markdown/images/h6.png
django_markdown/static/django_markdown/sets/markdown/images/image.png
django_markdown/static/django_markdown/sets/markdown/images/italic.png
django_markdown/static/django_markdown/sets/markdown/images/link.png
django_markdown/static/django_markdown/sets/markdown/images/list-bullet.png
django_markdown/static/django_markdown/sets/markdown/images/list-numeric.png
django_markdown/static/django_markdown/sets/markdown/images/picture.png
django_markdown/static/django_markdown/sets/markdown/images/preview.png
django_markdown/static/django_markdown/sets/markdown/images/quotes.png
django_markdown/static/django_markdown/sets/markdown/images/stroke.png
django_markdown/static/django_markdown/sets/markdownextra/set.js
