Metadata-Version: 2.0
Name: django2-markdown
Version: 0.8.6
Summary: Django markdown support and wysiwyg.
Requires-Dist: django
Requires-Dist: markdown
